lintcheck/__init__.py
lintcheck/extension.py
lintcheck/py.typed
lintcheck/utils.py
lintcheck-1.0.1.dist-info/LICENSE
lintcheck-1.0.1.dist-info/METADATA
lintcheck-1.0.1.dist-info/WHEEL
lintcheck-1.0.1.dist-info/entry_points.txt
lintcheck-1.0.1.dist-info/top_level.txt
lintcheck-1.0.1.dist-info/RECORD
